[
  {
    "py/object": "model.project.Project",
    "id": null,
    "name": "",
    "status": "",
    "view_status": "",
    "description": ""
  },
  {
    "py/object": "model.project.Project",
    "id": null,
    "name": "project-nameD4",
    "status": "release",
    "view_status": "private",
    "description": "desc34"
  },
  {
    "py/object": "model.project.Project",
    "id": null,
    "name": "project-name4",
    "status": "release",
    "view_status": "private",
    "description": "desc16"
  },
  {
    "py/object": "model.project.Project",
    "id": null,
    "name": "project-nameytPn",
    "status": "development",
    "view_status": "public",
    "description": "desc2"
  },
  {
    "py/object": "model.project.Project",
    "id": null,
    "name": "project-namecp",
    "status": "development",
    "view_status": "public",
    "description": "desc1"
  },
  {
    "py/object": "model.project.Project",
    "id": null,
    "name": "project-namePykwmqesR",
    "status": "development",
    "view_status": "public",
    "description": "desc5"
  },
  {
    "py/object": "model.project.Project",
    "id": null,
    "name": "project-name S",
    "status": "development",
    "view_status": "public",
    "description": "desc44"
  },
  {
    "py/object": "model.project.Project",
    "id": null,
    "name": "project-namei i  hP",
    "status": "development",
    "view_status": "private",
    "description": "desc19"
  },
  {
    "py/object": "model.project.Project",
    "id": null,
    "name": "project-namehvza",
    "status": "development",
    "view_status": "private",
    "description": "desc29"
  },
  {
    "py/object": "model.project.Project",
    "id": null,
    "name": "project-nameoj",
    "status": "development",
    "view_status": "private",
    "description": "desc2"
  },
  {
    "py/object": "model.project.Project",
    "id": null,
    "name": "project-nameb",
    "status": "release",
    "view_status": "private",
    "description": "desc11"
  },
  {
    "py/object": "model.project.Project",
    "id": null,
    "name": "project-nameMXkrIfOr",
    "status": "development",
    "view_status": "public",
    "description": "desc48"
  },
  {
    "py/object": "model.project.Project",
    "id": null,
    "name": "project-nameenv",
    "status": "release",
    "view_status": "private",
    "description": "desc13"
  },
  {
    "py/object": "model.project.Project",
    "id": null,
    "name": "project-name",
    "status": "development",
    "view_status": "private",
    "description": "desc6"
  },
  {
    "py/object": "model.project.Project",
    "id": null,
    "name": "project-nameOYqG F7i",
    "status": "release",
    "view_status": "private",
    "description": "desc3"
  },
  {
    "py/object": "model.project.Project",
    "id": null,
    "name": "project-nameycnOkmtf",
    "status": "release",
    "view_status": "public",
    "description": "desc32"
  },
  {
    "py/object": "model.project.Project",
    "id": null,
    "name": "project-nameoin M3",
    "status": "development",
    "view_status": "private",
    "description": "desc34"
  },
  {
    "py/object": "model.project.Project",
    "id": null,
    "name": "project-namem9mjeo ",
    "status": "release",
    "view_status": "public",
    "description": "desc41"
  },
  {
    "py/object": "model.project.Project",
    "id": null,
    "name": "project-namefxDsQOc",
    "status": "release",
    "view_status": "private",
    "description": "desc40"
  },
  {
    "py/object": "model.project.Project",
    "id": null,
    "name": "project-namewZq F4wq",
    "status": "development",
    "view_status": "public",
    "description": "desc19"
  },
  {
    "py/object": "model.project.Project",
    "id": null,
    "name": "project-nameef3K",
    "status": "release",
    "view_status": "private",
    "description": "desc19"
  }
]